STEM/__init__.py
STEM/evaluate.py
STEM/model.py
STEM/utils.py
scSTEM-0.0.2.dist-info/LICENSE
scSTEM-0.0.2.dist-info/METADATA
scSTEM-0.0.2.dist-info/WHEEL
scSTEM-0.0.2.dist-info/top_level.txt
scSTEM-0.0.2.dist-info/RECORD
