Metadata-Version: 2.1
Name: scSTEM
Version: 0.0.2
Summary: A Method for Mapping Single-cell and Spatial Transcriptomics Data with Transfer Learning
Home-page: https://github.com/WhirlFirst/STEM
Author: whirl
Author-email: hmsh653@gmail.com
License: UNKNOWN
Platform: UNKNOWN
Classifier: Programming Language :: Python :: 3
Classifier: Operating System :: OS Independent
Requires-Python: >=3.8
Requires-Dist: scanpy (>=1.8.2)
Requires-Dist: tqdm (>=4.60.0)
Requires-Dist: seaborn (>=0.11.1)
